configmixin/__init__.py
configmixin/_core.py
configmixin/_json.py
just_config_mixin-0.1.1.dist-info/LICENSE
just_config_mixin-0.1.1.dist-info/METADATA
just_config_mixin-0.1.1.dist-info/WHEEL
just_config_mixin-0.1.1.dist-info/RECORD
