Metadata-Version: 2.3
Name: just-config-mixin
Version: 0.1.1
Summary: Yet another config mixin/manager.
License: Apache License
Author: guest400123064
Author-email: wangy49@seas.upenn.edu
Requires-Python: >=3.10
Classifier: License :: Other/Proprietary License
Classifier: Programming Language :: Python :: 3
Classifier: Programming Language :: Python :: 3.10
Classifier: Programming Language :: Python :: 3.11
Classifier: Programming Language :: Python :: 3.12
Classifier: Programming Language :: Python :: 3.13
Requires-Dist: orjson (>=3.11.1,<4.0.0)
